benchmarks/__init__.py
benchmarks/__main__.py
benchmarks/_helpers.py
benchmarks/benchmarks.py
sew/__init__.py
sew/_core.py
sew/blobInterpreter.py
sew/condition.py
sew/formatSpec.py
sew/plugins.py
tests/__init__.py
tests/__main__.py
tests/_helpers.py
tests/blobs.py
tests/correctness.py
s3ew-0.0.4.dist-info/LICENSE
s3ew-0.0.4.dist-info/METADATA
s3ew-0.0.4.dist-info/WHEEL
s3ew-0.0.4.dist-info/top_level.txt
s3ew-0.0.4.dist-info/RECORD
