Metadata-Version: 2.1
Name: s3ew
Version: 0.0.4
Summary: Sqlite Extensions and Wrappers
Author: icyveins7
License: MIT License
Project-URL: Repository, https://github.com/icyveins7/sew
Keywords: sqlite,wrapper,extensions
License-File: LICENSE
Provides-Extra: plugins
Requires-Dist: numpy ; extra == 'plugins'
Requires-Dist: pandas ; extra == 'plugins'
Requires-Dist: python-dateutil ; extra == 'plugins'
Requires-Dist: pytz ; extra == 'plugins'
Requires-Dist: six ; extra == 'plugins'
Requires-Dist: tzdata ; extra == 'plugins'
